rest_mysql/Record_Base.py
rest_mysql/Record_MySQL.py
rest_mysql/__init__.py
rest_mysql-1.2.6.dist-info/METADATA
rest_mysql-1.2.6.dist-info/WHEEL
rest_mysql-1.2.6.dist-info/licenses/LICENSE
rest_mysql-1.2.6.dist-info/RECORD
