Metadata-Version: 2.4
Name: rest_mysql
Version: 1.2.6
Summary: Stand alone version of Record_MySQL from Rest-OC to facilitate updating code to newer librairies. Has since been updated far beyond Rest-OC.
Project-URL: Source, https://github.com/ouroboroscoding/rest_mysql
Project-URL: Tracker, https://github.com/ouroboroscoding/rest_mysql/issues
Author-email: "Chris Nasr - Ouroboros Coding Inc." <chris@ouroboroscoding.com>
Maintainer-email: "Chris Nasr - Ouroboros Coding Inc." <chris@ouroboroscoding.com>
License-Expression: MIT
License-File: LICENSE
Requires-Python: >=3.10
Requires-Dist: arrow<1.4,>=1.3.0
Requires-Dist: config-oc<1.2,>=1.1.0
Requires-Dist: dbutils<3.2,>=3.1.0
Requires-Dist: define-oc<1.1,>=1.0.5
Requires-Dist: json-fix<1.1,>=1.0.0
Requires-Dist: jsonb<1.1,>=1.0.0
Requires-Dist: pymysql<1.2,>=1.1.1
Requires-Dist: tools-oc<1.3,>=1.2.5
